aockit/__init__.py
aockit/grid.py
aockit/inputs.py
aockit/test/__init__.py
aockit/test/assets/input_char_grid.txt
aockit/test/assets/input_int_grid.txt
aockit/test/assets/input_int_groups.txt
aockit/test/assets/input_ints.txt
aockit/test/assets/input_string_groups.txt
aockit/test/assets/input_strings.txt
aockit/test/test_grid.py
aockit/test/test_inputs.py
aockit-1.0.2.dist-info/METADATA
aockit-1.0.2.dist-info/WHEEL
aockit-1.0.2.dist-info/RECORD
