Metadata-Version: 2.1
Name: aockit
Version: 1.0.2
Summary: A set of common utilities for completing the Advent of Code.
Author: Scott Odle
Author-email: scott@sjodle.com
Requires-Python: >=3.9,<4.0
Classifier: Programming Language :: Python :: 3
Classifier: Programming Language :: Python :: 3.9
Classifier: Programming Language :: Python :: 3.10
Classifier: Programming Language :: Python :: 3.11
Classifier: Programming Language :: Python :: 3.12
